[
  {
    "name": "C. Riley Snorton",
    "slug": "c.-riley-snorton"
  },
  {
    "name": "Silvia Federici",
    "slug": "silvia-federici"
  },
  {
    "name": "Sven Beckert",
    "slug": "sven-beckert"
  },
  {
    "name": "Patricia Hill Collins",
    "slug": "patricia-hill-collins"
  },
  {
    "name": "Carole Boyce Davies",
    "slug": "carole-boyce-davies"
  },
  {
    "name": "Erik M. Baker",
    "slug": "erik-m.-baker"
  },
  {
    "name": "Nick Estes",
    "slug": "nick-estes"
  },
  {
    "name": "Pierre Odin",
    "slug": "pierre-odin"
  },
  {
    "name": "Stuart Hall",
    "slug": "stuart-hall"
  },
  {
    "name": "Olufemi O. Taiwo",
    "slug": "olufemi-o.-taiwo"
  },
  {
    "name": "Amilcar Cabral",
    "slug": "amilcar-cabral"
  },
  {
    "name": "Rashid Khalidi",
    "slug": "rashid-khalidi"
  },
  {
    "name": "Ula Yvette Taylor",
    "slug": "ula-yvette-taylor"
  },
  {
    "name": "Ashley Jardina",
    "slug": "ashley-jardina"
  },
  {
    "name": "Lloyd Best",
    "slug": "lloyd-best"
  }
]